koko_keywords/__init__.py
koko_keywords/koko_keywords.py
koko_keywords/clib/libkoko_keywords_arm64.dylib
koko_keywords/clib/libkoko_keywords_arm64.so
koko_keywords/clib/libkoko_keywords_x86_64.dylib
koko_keywords/clib/libkoko_keywords_x86_64.so
koko_keywords-0.3.2.dist-info/METADATA
koko_keywords-0.3.2.dist-info/WHEEL
koko_keywords-0.3.2.dist-info/top_level.txt
koko_keywords-0.3.2.dist-info/RECORD
