Metadata-Version: 2.4
Name: koko_keywords
Version: 0.3.2
Summary: A python client  for the Koko Keywords API. The client handles caching to ensure very low latency.
Home-page: https://github.com/kokocares/keywords-client/python/client
Author: Kareem Kouddous
Author-email: api@kokocares.org
License: MIT
Project-URL: Documentation, https://github.com/kokocares/keywords-client/tree/main/clients/python
Project-URL: Source, https://github.com/kokocares/keywords-client/tree/main/clients/python
Project-URL: Tracker, https://github.com/kokocares/keywords-client/issues
Classifier: Development Status :: 4 - Beta
Classifier: Intended Audience :: Developers
Classifier: Topic :: Software Development :: Build Tools
Classifier: License :: OSI Approved :: MIT License
Classifier: Programming Language :: Python :: 3
Classifier: Programming Language :: Python :: 3.6
Classifier: Programming Language :: Python :: 3.7
Classifier: Programming Language :: Python :: 3.8
Classifier: Programming Language :: Python :: 3.9
Requires-Python: >=3
Requires-Dist: cffi>=1.15.0
Dynamic: author
Dynamic: author-email
Dynamic: classifier
Dynamic: description
Dynamic: description-content-type
Dynamic: home-page
Dynamic: license
Dynamic: project-url
Dynamic: requires-dist
Dynamic: requires-python
Dynamic: summary
